__init__.py
config.py
main.py
model_run.py
utils.py
data/__init__.py
data/dataio.py
data/dataloader.py
inference/__init__.py
inference/inference.py
preprocess/__init__.py
preprocess/countryset.py
preprocess/ner.py
preprocess/preprocessing.py
preprocess/textrank.py
trainer/__init__.py
trainer/nlp_model.py
Newspiece-1.6.dist-info/METADATA
Newspiece-1.6.dist-info/WHEEL
Newspiece-1.6.dist-info/top_level.txt
Newspiece-1.6.dist-info/RECORD
