Metadata-Version: 2.1
Name: Newspiece
Version: 1.6
Summary: Tacademy project의 newsmodel을 학습하고 실험하기 위한 패키지 입니다.
Home-page: https://github.com/JuwonOh/Tacademy-project
Author: Juwon Oh, Jinho Han
Author-email: 13a71032776@gmail.com
License: MIT License
Download-URL: https://github.com/JuwonOh/Tacademy-project/tree/main/NewsModel
Keywords: NLP,pytorch,Sentiment analysis
Platform: UNKNOWN
Classifier: Programming Language :: Python :: 3
Classifier: License :: OSI Approved :: MIT License
Classifier: Operating System :: OS Independent
Requires-Python: >=3.8
Requires-Dist: torch (==1.11.0)
Requires-Dist: mlflow (==1.24.0)
Requires-Dist: scikit-learn (==1.0.2)
Requires-Dist: transformers (==4.0)
Requires-Dist: scipy (==1.7.1)
